cloudutils/__init__.py
cloudutils/core/__init__.py
cloudutils/core/client.py
cloudutils/core/config.py
cloudutils/core/database.py
cloudutils/core/logging.py
cloudutils/core/network.py
cloudutils/core/service.py
cloudutils/core/utils.py
cloudutils/model/__init__.py
cloudutils/model/base.py
cloudutils/model/complex.py
cloudutils/model/fault.py
cloudutils/model/request.py
cloudutils-1.3.19.dist-info/METADATA
cloudutils-1.3.19.dist-info/WHEEL
cloudutils-1.3.19.dist-info/top_level.txt
cloudutils-1.3.19.dist-info/RECORD
