Metadata-Version: 2.1
Name: cloudutils
Version: 1.3.19
Summary: Utilities for Cloud applications
Home-page: https://github.com/NoelKaczmarek/cloudutils
Author: Noel Kaczmarek
Author-email: noel.Kaczmarek@gmail.com
License: UNKNOWN
Download-URL: https://github.com/NoelKaczmarek/cloudutils/archive/1.0.0.tar.gz
Keywords: cloud utils
Platform: UNKNOWN
Classifier: Programming Language :: Python :: 3
Classifier: Operating System :: OS Independent
